dataclassesapi/__init__.py
dataclassesapi/app.py
dataclassesapi/exceptions.py
dataclassesapi/method.py
dataclassesapi/request.py
dataclassesapi/response.py
dataclassesapi/router.py
dataclassesapi/tests/test_app.py
dataclassesapi/tests/test_router.py
dataclassesapi-0.2.0.dist-info/LICENSE
dataclassesapi-0.2.0.dist-info/WHEEL
dataclassesapi-0.2.0.dist-info/METADATA
dataclassesapi-0.2.0.dist-info/RECORD
