Metadata-Version: 2.1
Name: dataclassesapi
Version: 0.2.0
Summary: ASGI App using dataclasses module for request/response objects
Home-page: https://github.com/dutradda/dataclassesapi
License: UNKNOWN
Author: Diogo Dutra
Author-email: diogodutradamata@gmail.com
Requires-Python: >=3.7
Classifier: License :: OSI Approved :: MIT License
Classifier: Development Status :: 1 - Planning
Classifier: Intended Audience :: Developers
Classifier: Programming Language :: Python :: 3.7
Classifier: Programming Language :: Python :: 3.8
Classifier: Topic :: Software Development :: Libraries
Requires-Dist: dataclassesjson[orjson]
Requires-Dist: mkdocs; extra == "doc"
Requires-Dist: mkdocs-material; extra == "doc"
Requires-Dist: markdown-include; extra == "doc"
Requires-Dist: asgi-testclient; extra == "test"
Requires-Dist: bumpversion; extra == "test"
Requires-Dist: black; extra == "test"
Requires-Dist: flake8; extra == "test"
Requires-Dist: isort; extra == "test"
Requires-Dist: ipython; extra == "test"
Requires-Dist: mypy; extra == "test"
Requires-Dist: pytest-asyncio; extra == "test"
Requires-Dist: pytest-cov; extra == "test"
Requires-Dist: pytest-mock; extra == "test"
Requires-Dist: pytest>=5.1.1; extra == "test"
Requires-Dist: tox; extra == "test"
Requires-Dist: towncrier; extra == "test"
Requires-Dist: uvicorn; extra == "test"
Project-URL: Documentation, https://dutradda.github.io/dataclassesapi/
Provides-Extra: doc
Provides-Extra: test
